setup.py
model_package/__init__.py
model_package/linear_model_class.py
model_package/model_class.py
model_package.egg-info/PKG-INFO
model_package.egg-info/SOURCES.txt
model_package.egg-info/dependency_links.txt
model_package.egg-info/not-zip-safe
model_package.egg-info/top_level.txt