Metadata-Version: 1.0
Name: model-package
Version: 2.0
Summary: Implement Linear Regression
Home-page: UNKNOWN
Author: Alessio Polymeropoulos
Author-email: polymeropoulos@hotmail.com
License: UNKNOWN
Platform: UNKNOWN
